etathermlib/__init__.py
etathermlib/etatherm.py
etathermlib_patriktrestik-1.4.0.dist-info/METADATA
etathermlib_patriktrestik-1.4.0.dist-info/WHEEL
etathermlib_patriktrestik-1.4.0.dist-info/top_level.txt
etathermlib_patriktrestik-1.4.0.dist-info/RECORD
