Metadata-Version: 2.4
Name: etathermlib-PatrikTrestik
Version: 1.4.0
Summary: Etatherm heating regulation TCP interface library
Home-page: https://github.com/PatrikTrestik/etathermlib
Author: Patrik Trestik
Author-email: patrikt@volny.cz
Classifier: Programming Language :: Python :: 3
Classifier: License :: OSI Approved :: MIT License
Classifier: Operating System :: OS Independent
Dynamic: author
Dynamic: author-email
Dynamic: classifier
Dynamic: description
Dynamic: description-content-type
Dynamic: home-page
Dynamic: summary
